blockchain_csetakeoff/__init__.py
blockchain_csetakeoff/blockchain.py
blockchain_engineersplanet-0.0.1.dist-info/LICENCE
blockchain_engineersplanet-0.0.1.dist-info/METADATA
blockchain_engineersplanet-0.0.1.dist-info/WHEEL
blockchain_engineersplanet-0.0.1.dist-info/top_level.txt
blockchain_engineersplanet-0.0.1.dist-info/RECORD
